deephaven_plugin_microphone/__init__.py
deephaven_plugin_microphone/deephaven_plugin_microphone_object.py
deephaven_plugin_microphone/deephaven_plugin_microphone_type.py
deephaven_plugin_microphone/js_plugin.py
deephaven_plugin_microphone/register.py
deephaven_plugin_microphone/_js/package.json
deephaven_plugin_microphone/_js/dist/index.js
deephaven_plugin_microphone-0.0.1.dev0.dist-info/LICENSE
deephaven_plugin_microphone-0.0.1.dev0.dist-info/METADATA
deephaven_plugin_microphone-0.0.1.dev0.dist-info/WHEEL
deephaven_plugin_microphone-0.0.1.dev0.dist-info/entry_points.txt
deephaven_plugin_microphone-0.0.1.dev0.dist-info/top_level.txt
deephaven_plugin_microphone-0.0.1.dev0.dist-info/RECORD
