Metadata-Version: 2.1
Name: deephaven-plugin-microphone
Version: 0.0.1.dev0
Summary: Deephaven plugin for microphone input
Author: Mike Bender
Author-email: mikebender@deephaven.io
Keywords: deephaven,plugin,microphone,audio input
Platform: any
License-File: LICENSE
Requires-Dist: deephaven-core>=0.35.1
Requires-Dist: deephaven-plugin>=0.6.0
Requires-Dist: deephaven-plugin-utilities
